jazzy/__init__.py
jazzy/__main__.py
jazzy/api.py
jazzy/config.py
jazzy/core.py
jazzy/exception.py
jazzy/helpers.py
jazzy/logging.py
jazzy/model.py
jazzy/py.typed
jazzy/visualisation.py
jazzy-0.1.4.dist-info/LICENSE.rst
jazzy-0.1.4.dist-info/METADATA
jazzy-0.1.4.dist-info/WHEEL
jazzy-0.1.4.dist-info/entry_points.txt
jazzy-0.1.4.dist-info/RECORD
