Metadata-Version: 2.3
Name: jazzy
Version: 0.1.4
Summary: Jazzy allows calculating a set of atomic/molecular descriptors including the Gibbs free energy of hydration (kJ/mol), its polar/apolar components, and the hydrogen-bond strength of donor and acceptor atoms.
License: Apache-2.0
Author: Gian Marco Ghiandoni
Author-email: ghiandoni.g@gmail.com
Requires-Python: >=3.8.0,<4.0.0
Classifier: Development Status :: 3 - Alpha
Classifier: License :: OSI Approved :: Apache Software License
Classifier: Programming Language :: Python :: 3
Classifier: Programming Language :: Python :: 3.8
Classifier: Programming Language :: Python :: 3.9
Classifier: Programming Language :: Python :: 3.10
Classifier: Programming Language :: Python :: 3.11
Classifier: Programming Language :: Python :: 3.12
Classifier: Programming Language :: Python :: 3.13
Requires-Dist: click (>=8.0.4,<9.0.0)
Requires-Dist: kallisto (>=1.0.9,<2.0.0)
Requires-Dist: rdkit (==2024.3.1)
Project-URL: Changelog, https://github.com/AstraZeneca/jazzy/releases
Project-URL: Documentation, https://jazzy.readthedocs.io
Project-URL: Homepage, https://github.com/AstraZeneca/jazzy
Project-URL: Repository, https://github.com/AstraZeneca/jazzy
